osudroid_api_wrapper/__init__.py
osudroid_api_wrapper/classes/__init__.py
osudroid_api_wrapper/classes/replay.py
osudroid_api_wrapper/classes/score.py
osudroid_api_wrapper/classes/base/__init__.py
osudroid_api_wrapper/classes/base/beatmap.py
osudroid_api_wrapper/classes/base/modlist.py
osudroid_api_wrapper/classes/base/player.py
osudroid_api_wrapper/classes/base/mods/__init__.py
osudroid_api_wrapper/classes/base/mods/mod.py
osudroid_api_wrapper/classes/base/mods/mod_approachdifferent.py
osudroid_api_wrapper/classes/base/mods/mod_auto.py
osudroid_api_wrapper/classes/base/mods/mod_autopilot.py
osudroid_api_wrapper/classes/base/mods/mod_customspeed.py
osudroid_api_wrapper/classes/base/mods/mod_difficultyadjust.py
osudroid_api_wrapper/classes/base/mods/mod_doubletime.py
osudroid_api_wrapper/classes/base/mods/mod_easy.py
osudroid_api_wrapper/classes/base/mods/mod_flashlight.py
osudroid_api_wrapper/classes/base/mods/mod_freezeframe.py
osudroid_api_wrapper/classes/base/mods/mod_halftime.py
osudroid_api_wrapper/classes/base/mods/mod_hardrock.py
osudroid_api_wrapper/classes/base/mods/mod_hidden.py
osudroid_api_wrapper/classes/base/mods/mod_mirror.py
osudroid_api_wrapper/classes/base/mods/mod_muted.py
osudroid_api_wrapper/classes/base/mods/mod_nightcore.py
osudroid_api_wrapper/classes/base/mods/mod_nofail.py
osudroid_api_wrapper/classes/base/mods/mod_perfect.py
osudroid_api_wrapper/classes/base/mods/mod_precise.py
osudroid_api_wrapper/classes/base/mods/mod_random.py
osudroid_api_wrapper/classes/base/mods/mod_reallyeasy.py
osudroid_api_wrapper/classes/base/mods/mod_relax.py
osudroid_api_wrapper/classes/base/mods/mod_replayv6.py
osudroid_api_wrapper/classes/base/mods/mod_scorev2.py
osudroid_api_wrapper/classes/base/mods/mod_smallcircles.py
osudroid_api_wrapper/classes/base/mods/mod_suddendeath.py
osudroid_api_wrapper/classes/base/mods/mod_synesthesia.py
osudroid_api_wrapper/classes/base/mods/mod_traceable.py
osudroid_api_wrapper/classes/base/mods/mod_winddown.py
osudroid_api_wrapper-0.0.6.dist-info/licenses/LICENSE
osudroid_api_wrapper-0.0.6.dist-info/METADATA
osudroid_api_wrapper-0.0.6.dist-info/WHEEL
osudroid_api_wrapper-0.0.6.dist-info/top_level.txt
osudroid_api_wrapper-0.0.6.dist-info/RECORD
