Metadata-Version: 2.4
Name: osudroid-api-wrapper
Version: 0.0.6
Summary: Python api wrapper for osu!droid
Author-email: unclem <mannringyt11@gmail.com>
License: MIT License
Project-URL: Homepage, https://github.com/unclem2/osudroid-api-wrapper
Project-URL: Issues, https://github.com/unclem2/osudroid-api-wrapper/issues
Classifier: Programming Language :: Python :: 3
Classifier: Operating System :: OS Independent
Requires-Python: >=3.8
License-File: LICENSE
Requires-Dist: requests>=2.26.0
Requires-Dist: beautifulsoup4>=4.10.0
Requires-Dist: javaobj-py3>=0.4.4
Requires-Dist: stream_unzip>=0.0.99
Requires-Dist: python-dotenv>=1.0.0
Dynamic: license-file
